{"type":"View","props":{"width":720,"name":"UITask","height":1280,"autoDestroyAtClosed":true},"compId":2,"child":[{"type":"Sprite","props":{"y":34,"x":179,"width":421,"var":"Describe","name":"Describe","height":67},"compId":21,"child":[{"type":"Image","props":{"y":37,"x":181,"width":360,"skin":"youxi/ui_describe.png","presetID":2,"pivotY":34,"pivotX":180,"name":"baseboard","height":68},"compId":3},{"type":"Label","props":{"y":16,"x":22,"width":60,"var":"TaskNum","valign":"middle","text":"[1/1]","presetID":3,"name":"TaskNum","height":33,"fontSize":29,"color":"#ffd34a","bold":true,"align":"center"},"compId":4},{"type":"Label","props":{"y":36,"x":217,"wordWrap":false,"width":224,"var":"TaskContent","valign":"middle","text":"在时间结束前尽可能地吃金币","presetID":4,"pivotY":16,"pivotX":112,"overflow":"visible","name":"TaskContent","height":32,"fontSize":24,"font":"Microsoft YaHei","color":"#ffffff","bold":false,"align":"center"},"compId":5}]},{"type":"Label","props":{"y":412,"x":360,"width":178,"var":"TaskTime","valign":"middle","text":"5S","strokeColor":"#2a283b","stroke":12,"presetID":5,"pivotY":25,"pivotX":89,"name":"TaskTime","height":50,"fontSize":42,"color":"#ffffff","bold":true,"alpha":1,"align":"center"},"compId":6},{"type":"Image","props":{"y":481,"x":360,"width":720,"var":"TaskLine","skin":"youxi/ui_line.png","pivotY":7,"pivotX":360,"name":"TaskLine","height":14},"compId":13},{"type":"Sprite","props":{"y":327,"x":600,"width":154,"var":"TaskCircle","texture":"youxi/ui_guide.png","pivotY":77,"pivotX":77,"name":"TaskCircle","height":154,"cacheAs":"none"},"compId":25},{"type":"Script","props":{"y":231,"x":353,"runtime":"script/Game/UITask.ts"},"compId":11}],"loadList":["youxi/ui_describe.png","prefab/UIdes.prefab","youxi/ui_line.png","youxi/ui_guide.png"],"loadList3D":[]}